jf_debug
