Metadata-Version: 2.1
Name: jf-debug
Version: 0.0.2
Summary: debug过程中辅助修饰方法
Home-page: https://gitlab.com/ImDePanDa/pyrelease
Author: DePanda
Author-email: 957454525@qq.com
License: UNKNOWN
Platform: UNKNOWN
Classifier: Programming Language :: Python :: 2
Classifier: License :: OSI Approved :: MIT License
Classifier: Operating System :: OS Independent
Requires-Python: >=2.7
